pyobvector/__init__.py
pyobvector/client/__init__.py
pyobvector/client/collection_schema.py
pyobvector/client/enum.py
pyobvector/client/exceptions.py
pyobvector/client/fts_index_param.py
pyobvector/client/hybrid_search.py
pyobvector/client/index_param.py
pyobvector/client/milvus_like_client.py
pyobvector/client/ob_client.py
pyobvector/client/ob_vec_client.py
pyobvector/client/ob_vec_json_table_client.py
pyobvector/client/partitions.py
pyobvector/client/schema_type.py
pyobvector/json_table/__init__.py
pyobvector/json_table/json_value_returning_func.py
pyobvector/json_table/oceanbase_dialect.py
pyobvector/json_table/virtual_data_type.py
pyobvector/schema/__init__.py
pyobvector/schema/array.py
pyobvector/schema/dialect.py
pyobvector/schema/full_text_index.py
pyobvector/schema/geo_srid_point.py
pyobvector/schema/gis_func.py
pyobvector/schema/match_against_func.py
pyobvector/schema/ob_table.py
pyobvector/schema/reflection.py
pyobvector/schema/replace_stmt.py
pyobvector/schema/sparse_vector.py
pyobvector/schema/vec_dist_func.py
pyobvector/schema/vector.py
pyobvector/schema/vector_index.py
pyobvector/util/__init__.py
pyobvector/util/ob_version.py
pyobvector/util/sparse_vector.py
pyobvector/util/vector.py
pyobvector-0.2.21.dist-info/METADATA
pyobvector-0.2.21.dist-info/WHEEL
pyobvector-0.2.21.dist-info/licenses/LICENSE
pyobvector-0.2.21.dist-info/RECORD
