Metadata-Version: 2.4
Name: pyobvector
Version: 0.2.21
Summary: A python SDK for OceanBase Vector Store, based on SQLAlchemy, compatible with Milvus API.
Project-URL: Homepage, https://github.com/oceanbase/pyobvector
Project-URL: Repository, https://github.com/oceanbase/pyobvector.git
Author-email: "shanhaikang.shk" <shanhaikang.shk@oceanbase.com>
License-Expression: Apache-2.0
License-File: LICENSE
Keywords: obvector,oceanbase,vector store
Requires-Python: >=3.9
Requires-Dist: aiomysql>=0.3.2
Requires-Dist: numpy>=1.17.0
Requires-Dist: pydantic<3,>=2.7.0
Requires-Dist: pymysql>=1.1.1
Requires-Dist: sqlalchemy<=3,>=1.4
Requires-Dist: sqlglot>=26.0.1
